LICENSE
README.md
setup.py
bin/bussilab
bussilab/__init__.py
bussilab/__main__.py
bussilab/_version.py
bussilab/ann.py
bussilab/cli.py
bussilab/cli_documentation.py
bussilab/clustering.py
bussilab/coretools.py
bussilab/cron.py
bussilab/jremote.py
bussilab/lohman.py
bussilab/maxent.py
bussilab/notify.py
bussilab/pip.py
bussilab/potts.py
bussilab/reports.py
bussilab/wham.py
bussilab.egg-info/PKG-INFO
bussilab.egg-info/SOURCES.txt
bussilab.egg-info/dependency_links.txt
bussilab.egg-info/requires.txt
bussilab.egg-info/top_level.txt
tests/test_ann.py
tests/test_cli.py
tests/test_clustering.py
tests/test_coretools.py
tests/test_cron.py
tests/test_lohman.py
tests/test_maxent.py
tests/test_notify.py
tests/test_potts.py
tests/test_wham.py